Metadata-Version: 2.1
Name: ontoledgy-bclearer-core
Version: 0.1.0
Summary: 
Author: Mesbah Khan
Author-email: khanm@ontoledgy.io
Requires-Python: >=3.12,<4.0
Classifier: Programming Language :: Python :: 3
Classifier: Programming Language :: Python :: 3.12
